a_pandas_ex_split_on_common_string/LICENSE
a_pandas_ex_split_on_common_string/README.MD
a_pandas_ex_split_on_common_string/__init__.py
a_pandas_ex_split_on_common_string/requirements.txt
a_pandas_ex_split_on_common_string/thirdparty.json
a_pandas_ex_split_on_common_string-0.10.dist-info/LICENSE.rst
a_pandas_ex_split_on_common_string-0.10.dist-info/METADATA
a_pandas_ex_split_on_common_string-0.10.dist-info/WHEEL
a_pandas_ex_split_on_common_string-0.10.dist-info/top_level.txt
a_pandas_ex_split_on_common_string-0.10.dist-info/RECORD
