Metadata-Version: 2.1
Name: a-pandas-ex-split-on-common-string
Version: 0.10
Summary: Split a Pandas.Series on a common string
Home-page: https://github.com/hansalemaos/a_pandas_ex_split_on_common_string
Author: Johannes Fischer
Author-email: <aulasparticularesdealemaosp@gmail.com>
License: MIT
Keywords: pandas,series,split
Classifier: Development Status :: 4 - Beta
Classifier: Programming Language :: Python :: 3 :: Only
Classifier: Programming Language :: Python :: 3.9
Classifier: Topic :: Scientific/Engineering :: Visualization
Classifier: Topic :: Software Development :: Libraries :: Python Modules
Classifier: Topic :: Text Editors :: Text Processing
Classifier: Topic :: Text Processing :: General
Classifier: Topic :: Text Processing :: Indexing
Classifier: Topic :: Text Processing :: Filters
Classifier: Topic :: Utilities
License-File: LICENSE.rst
Requires-Dist: a-pandas-ex-df-to-string
Requires-Dist: a-pandas-ex-plode-tool
Requires-Dist: pandas
Requires-Dist: regex
